glaciers-2.0.2.dist-info/METADATA
glaciers-2.0.2.dist-info/WHEEL
glaciers/__init__.py
glaciers/_abi_reader.py
glaciers/_dataframe_utils.py
glaciers/_decode_df.py
glaciers/_decode_df_using_single_contract.py
glaciers/_decode_df_with_abi_df.py
glaciers/_decode_file.py
glaciers/_decode_folder.py
glaciers/_glaciers_python.cpython-39-darwin.so
glaciers/_unnest.py
glaciers-2.0.2.dist-info/RECORD
