Metadata-Version: 2.4
Name: glaciers
Version: 2.0.2
Classifier: Programming Language :: Rust
Classifier: Programming Language :: Python :: Implementation :: CPython
Classifier: Programming Language :: Python :: Implementation :: PyPy
Requires-Dist: maturin>=1.7.8
Requires-Dist: polars>=1.17.1
Requires-Dist: pyarrow>=18.1.0
Requires-Dist: toml>=0.10.0
Requires-Dist: pandas>=2.1.1
Summary: Glaciers is a rust python bindings to decode raw EVM logs/traces into decoded events.
Home-Page: https://github.com/yulesa/glaciers
License: MIT OR Apache-2.0
Requires-Python: >=3.11
Project-URL: Source Code, https://github.com/yulesa/glaciers
